element_calcium_imaging/__init__.py
element_calcium_imaging/analysis.py
element_calcium_imaging/imaging.py
element_calcium_imaging/imaging_no_curation.py
element_calcium_imaging/imaging_preprocess.py
element_calcium_imaging/imaging_report.py
element_calcium_imaging/scan.py
element_calcium_imaging/version.py
element_calcium_imaging/plotting/__init__.py
element_calcium_imaging/plotting/cell_plot.py
element_calcium_imaging/plotting/widget.py
element_calcium_imaging-0.7.8.dist-info/LICENSE
element_calcium_imaging-0.7.8.dist-info/METADATA
element_calcium_imaging-0.7.8.dist-info/WHEEL
element_calcium_imaging-0.7.8.dist-info/top_level.txt
element_calcium_imaging-0.7.8.dist-info/RECORD
