Metadata-Version: 2.1
Name: element-calcium-imaging
Version: 0.7.8
Summary: Calcium Imaging DataJoint Element
Home-page: https://github.com/datajoint/element-calcium-imaging
Author: DataJoint
Author-email: info@datajoint.com
License: MIT
Keywords: neuroscience calcium-imaging science datajoint
Platform: UNKNOWN
License-File: LICENSE
Requires-Dist: datajoint (>=0.13.0)
Requires-Dist: ipykernel (>=6.0.1)
Requires-Dist: ipywidgets
Requires-Dist: plotly
Provides-Extra: elements
Requires-Dist: element-animal (>=0.1.8) ; extra == 'elements'
Requires-Dist: element-event (>=0.2.3) ; extra == 'elements'
Requires-Dist: element-interface (>=0.5.4) ; extra == 'elements'
Requires-Dist: element-lab (>=0.3.0) ; extra == 'elements'
Requires-Dist: element-session (>=0.1.5) ; extra == 'elements'
Provides-Extra: extract
Requires-Dist: matlabengine ; extra == 'extract'
Requires-Dist: scipy ; extra == 'extract'
Provides-Extra: nd2
Requires-Dist: nd2 ; extra == 'nd2'
Provides-Extra: suite2p
Requires-Dist: suite2p[io] (>=0.12.1) ; extra == 'suite2p'
Provides-Extra: tests
Requires-Dist: pytest ; extra == 'tests'
Requires-Dist: pytest-cov ; extra == 'tests'
Requires-Dist: shutils ; extra == 'tests'
